LICENSE
README.rst
pornhub_api/__init__.py
pornhub_api/api.py
pornhub_api/backends/__init__.py
pornhub_api/backends/aiohttp.py
pornhub_api/backends/base.py
pornhub_api/backends/httpx.py
pornhub_api/backends/requests.py
pornhub_api/exceptions/__init__.py
pornhub_api/exceptions/response.py
pornhub_api/modules/__init__.py
pornhub_api/modules/base.py
pornhub_api/modules/search.py
pornhub_api/modules/stars.py
pornhub_api/modules/video.py
pornhub_api/schemas/__init__.py
pornhub_api/schemas/category.py
pornhub_api/schemas/pornstart.py
pornhub_api/schemas/search.py
pornhub_api/schemas/star.py
pornhub_api/schemas/tag.py
pornhub_api/schemas/thumb.py
pornhub_api/schemas/video.py
pornhub_api-0.4.0.dist-info/LICENSE
pornhub_api-0.4.0.dist-info/METADATA
pornhub_api-0.4.0.dist-info/WHEEL
pornhub_api-0.4.0.dist-info/RECORD
