Metadata-Version: 2.1
Name: pornhub-api
Version: 0.4.0
Summary: 
Home-page: https://github.com/Derfirm/pornhub_api
License: MIT
Keywords: pornhub,pornhub-api,api-wrapper
Author: Andrew Grinevich
Author-email: beule@gmail.com
Requires-Python: >=3.9,<3.13
Classifier: Development Status :: 2 - Pre-Alpha
Classifier: Intended Audience :: Information Technology
Classifier: License :: OSI Approved :: MIT License
Classifier: Natural Language :: English
Classifier: Operating System :: OS Independent
Classifier: Programming Language :: Python
Classifier: Programming Language :: Python :: 3
Classifier: Programming Language :: Python :: 3.9
Classifier: Programming Language :: Python :: 3.10
Classifier: Programming Language :: Python :: 3.11
Classifier: Programming Language :: Python :: 3.12
Classifier: Topic :: Internet :: WWW/HTTP
Classifier: Topic :: Software Development :: Libraries :: Python Modules
Provides-Extra: aiohttp-backend
Provides-Extra: httpx-backend
Requires-Dist: aiohttp (>=3.11.5,<4.0.0) ; extra == "aiohttp-backend"
Requires-Dist: httpx (>=0.23.1) ; extra == "httpx-backend"
Requires-Dist: pydantic (>=1.4,<2.0)
Requires-Dist: requests (>=2.23.0)
Project-URL: Repository, https://github.com/Derfirm/pornhub_api
